vedium_multiply/__init__.py
vedium_multiply/multiplication.py
vedium_multiply-0.1.1.dist-info/METADATA
vedium_multiply-0.1.1.dist-info/WHEEL
vedium_multiply-0.1.1.dist-info/top_level.txt
vedium_multiply-0.1.1.dist-info/RECORD
